NoteBookServer
