Metadata-Version: 1.1
Name: notebookserver
Version: 0.14
Summary: notebookserver for DataCanvas.
Home-page: UNKNOWN
Author: liujie
Author-email: liujie@zetyun.com
License: UNKNOWN
Platform: UNKNOWN
Classifier: Development Status :: 4 - Beta
Classifier: Environment :: Other Environment
Classifier: Intended Audience :: Developers
Classifier: Operating System :: OS Independent
Classifier: Programming Language :: Python
Classifier: Programming Language :: Python :: 2.7
Classifier: Topic :: Utilities
Classifier: License :: OSI Approved :: Apache Software License
